setup.py
BelarusBank/__init__.py
BelarusBank/aiobelarusbankapi.py
BelarusBank/belarusbankapi.py
BelarusBank.egg-info/PKG-INFO
BelarusBank.egg-info/SOURCES.txt
BelarusBank.egg-info/dependency_links.txt
BelarusBank.egg-info/not-zip-safe
BelarusBank.egg-info/requires.txt
BelarusBank.egg-info/top_level.txt