Metadata-Version: 2.1
Name: BelarusBank
Version: 1.1.0
Summary: Оболочка для использования BelarusBankAPI на Python
Author: Barl
Author-email: adwer197@gmail.com
Classifier: Programming Language :: Python :: 3.7
Classifier: Programming Language :: Python :: 3.8
Classifier: Programming Language :: Python :: 3.9
Classifier: Programming Language :: Python :: 3.10
Classifier: License :: OSI Approved :: MIT License
Classifier: Operating System :: OS Independent
